Tweet/Tweet.py
Tweet/__init__.py
Tweet/file.py
Tweet/upload.py
tweeter_basic-0.1.1.dist-info/METADATA
tweeter_basic-0.1.1.dist-info/WHEEL
tweeter_basic-0.1.1.dist-info/top_level.txt
tweeter_basic-0.1.1.dist-info/RECORD
