Metadata-Version: 2.1
Name: tweeter-basic
Version: 0.1.1
Summary: Send tweets (with optional images) through the Twitter v2 API (OAuth 2.0) - authentication included
Home-page: https://mike.busuttil.ca/
Author: Mike Busuttil
Author-email: mike@busuttil.ca
License: MIT
Keywords: tweet,twitter,v2,OAuth,OAuth2.0,API,images
Platform: UNKNOWN
Classifier: Development Status :: 5 - Production/Stable
Classifier: Intended Audience :: Developers
Classifier: License :: OSI Approved :: MIT License
Classifier: Programming Language :: Python :: 3
Classifier: Topic :: Education
Classifier: Topic :: Software Development
Classifier: Topic :: Software Development :: Libraries
Classifier: Topic :: Software Development :: Libraries :: Python Modules
Requires-Dist: flask
Requires-Dist: requests
Requires-Dist: requests-oauthlib
